Metadata-Version: 2.1
Name: mpqobdt
Version: 0.0.2
Summary: object detection for MPQ
Home-page: https://github.com/miaopeiqi
Author: MPQ
Author-email: miaopeiqi@163.com
License: UNKNOWN
Platform: UNKNOWN
